lens/__init__.py
lens/admin.py
lens/apps.py
lens/middleware.py
lens/models.py
lens/traces.py
lens/urls.py
lens/utils.py
lens/views.py
lens/migrations/0001_initial.py
lens/migrations/0002_auto_20210815_0029.py
lens/migrations/__init__.py
lens/static/lens/css/lens.css
lens/static/lens/css/tailwind.min.css
lens/static/lens/js/htmx.min.js
lens/static/lens/js/lens.js
lens/templates/lens/base.html
lens/templates/lens/detail.html
lens/templates/lens/list.html
lens/templates/lens/settings.html
lens/templates/lens/components/client_request_detail.html
lens/templates/lens/components/client_request_summary.html
lens/templates/lens/components/codeblock.html
lens/templates/lens/components/duration.html
lens/templates/lens/components/empty_trace.html
lens/templates/lens/components/headers.html
lens/templates/lens/components/method.html
lens/templates/lens/components/sql_detail.html
lens/templates/lens/components/sql_summary.html
lens/templates/lens/components/stacktrace.html
lens/templates/lens/components/status.html
lens/templates/lens/components/trace_list.html
lens/templates/lens/panels/client_request.html
lens/templates/lens/panels/print.html
lens/templates/lens/panels/request.html
lens/templates/lens/panels/request_payload.html
lens/templates/lens/panels/response_data.html
lens/templates/lens/panels/sql.html
lens/templates/lens/panels/sql_detailed.html
lens/templatetags/__init__.py
lens/templatetags/lens_tags.py
lens/test_utils/__init__.py
lens/test_utils/test_app/__init__.py
lens/test_utils/test_app/admin.py
lens/test_utils/test_app/apps.py
lens/test_utils/test_app/models.py
lens/test_utils/test_app/migrations/__init__.py
lens/watchers/__init__.py
lens/watchers/base.py
lens/watchers/client_request.py
lens/watchers/print.py
lens/watchers/request.py
lens/watchers/sql.py
django_lens-0.0.2.dist-info/AUTHORS.rst
django_lens-0.0.2.dist-info/LICENSE
django_lens-0.0.2.dist-info/METADATA
django_lens-0.0.2.dist-info/WHEEL
django_lens-0.0.2.dist-info/top_level.txt
django_lens-0.0.2.dist-info/RECORD
