Metadata-Version: 2.1
Name: django-lens
Version: 0.0.2
Summary: Enhance your Django development experience
Home-page: https://github.com/v1k45/django-lens
Author: Vikas Yadav
Author-email: vikas@v1k45.com
License: MIT
Keywords: django-lens
Classifier: Development Status :: 3 - Alpha
Classifier: Framework :: Django :: 1.11
Classifier: Framework :: Django :: 2.1
Classifier: Intended Audience :: Developers
Classifier: License :: OSI Approved :: BSD License
Classifier: Natural Language :: English
Classifier: Programming Language :: Python :: 2
Classifier: Programming Language :: Python :: 2.7
Classifier: Programming Language :: Python :: 3
Classifier: Programming Language :: Python :: 3.5
Classifier: Programming Language :: Python :: 3.6
License-File: LICENSE
License-File: AUTHORS.rst
Requires-Dist: django-model-utils (>=2.0)
Requires-Dist: jsonfield
Requires-Dist: requests
Requires-Dist: asgiref
Requires-Dist: sqlparse
